{
  "runtime": "NetCore21",
  "defaultVariables": null,
  "documentGenerator": {
    "fromDocument": {
      "url": "http://localhost:8080/api/docs-json",
      "output": null
    }
  },
  "codeGenerators": {
    "openApiToTypeScriptClient": {
      "className": "{controller}Client",
      "typeScriptVersion": 3.8,
      "template": "Angular",
      "promiseType": "Promise",
      "httpClass": "HttpClient",
      "withCredentials": false,
      "useSingletonProvider": true,
      "injectionTokenType": "InjectionToken",
      "rxJsVersion": 6.0,
      "dateTimeType": "Date",
      "nullValue": "Null",
      "generateClientClasses": true,
      "generateClientInterfaces": false,
      "generateOptionalParameters": true,
      "exportTypes": true,
      "wrapDtoExceptions": false,
      "exceptionClass": "SwaggerException",
      "clientBaseClass": null,
      "wrapResponses": false,
      "wrapResponseMethods": [],
      "generateResponseClasses": true,
      "responseClass": "SwaggerResponse",
      "protectedMethods": [],
      "configurationClass": null,
      "useTransformOptionsMethod": false,
      "useTransformResultMethod": false,
      "generateDtoTypes": true,
      "operationGenerationMode": "MultipleClientsFromOperationId",
      "markOptionalProperties": true,
      "generateCloneMethod": false,
      "typeStyle": "Class",
      "enumStyle": "Enum",
      "useLeafType": false,
      "classTypes": [],
      "extendedClasses": [],
      "extensionCode": null,
      "generateDefaultValues": true,
      "excludedTypeNames": [],
      "excludedParameterNames": [],
      "handleReferences": false,
      "generateConstructorInterface": false,
      "convertConstructorInterfaceData": false,
      "importRequiredTypes": true,
      "useGetBaseUrlMethod": false,
      "baseUrlTokenName": "API_BASE_URL",
      "queryNullValue": "",
      "inlineNamedDictionaries": false,
      "inlineNamedAny": false,
      "templateDirectory": null,
      "typeNameGeneratorType": null,
      "propertyNameGeneratorType": null,
      "enumNameGeneratorType": null,
      "serviceHost": null,
      "serviceSchemes": null,
      "output": "./libs/client/nswag/src/lib/api.client.ts"
    }
  }
}
